Cellcyto/GUI.py
Cellcyto/GUI_POSEA.py
Cellcyto/GUI_postprocessing.py
Cellcyto/__init__.py
Cellcyto-1.8.1.dist-info/LICENSE.txt
Cellcyto-1.8.1.dist-info/METADATA
Cellcyto-1.8.1.dist-info/WHEEL
Cellcyto-1.8.1.dist-info/entry_points.txt
Cellcyto-1.8.1.dist-info/top_level.txt
Cellcyto-1.8.1.dist-info/RECORD
